WangluoJibengongXilie/README.md
WangluoJibengongXilie/__init__.py
WangluoJibengongXilie/__main__.py
WangluoJibengongXilie/file.epub
WangluoJibengongXilie/index.html
WangluoJibengongXilie/css/__init__.py
WangluoJibengongXilie/css/annotations.css
WangluoJibengongXilie/css/main.css
WangluoJibengongXilie/css/normalize.css
WangluoJibengongXilie/css/popup.css
WangluoJibengongXilie/font/__init__.py
WangluoJibengongXilie/font/fontello.eot
WangluoJibengongXilie/font/fontello.svg
WangluoJibengongXilie/font/fontello.ttf
WangluoJibengongXilie/font/fontello.woff
WangluoJibengongXilie/img/__init__.py
WangluoJibengongXilie/img/annotator-glyph-sprite.png
WangluoJibengongXilie/img/annotator-icon-sprite.png
WangluoJibengongXilie/img/apple-touch-icon.png
WangluoJibengongXilie/img/cancelfullscreen.png
WangluoJibengongXilie/img/close.png
WangluoJibengongXilie/img/fullscreen.png
WangluoJibengongXilie/img/loader.gif
WangluoJibengongXilie/img/menu-icon.png
WangluoJibengongXilie/img/save.png
WangluoJibengongXilie/img/saved.png
WangluoJibengongXilie/img/settings-s.png
WangluoJibengongXilie/img/settings.png
WangluoJibengongXilie/img/star.png
WangluoJibengongXilie/js/__init__.py
WangluoJibengongXilie/js/epub.js
WangluoJibengongXilie/js/epub.min.js
WangluoJibengongXilie/js/epub.min.map
WangluoJibengongXilie/js/hooks.min.js
WangluoJibengongXilie/js/hooks.min.map
WangluoJibengongXilie/js/reader.js
WangluoJibengongXilie/js/reader.js.map
WangluoJibengongXilie/js/reader.min.js
WangluoJibengongXilie/js/reader.min.map
WangluoJibengongXilie/js/hooks/__init__.py
WangluoJibengongXilie/js/hooks/extensions/__init__.py
WangluoJibengongXilie/js/hooks/extensions/highlight.js
WangluoJibengongXilie/js/libs/__init__.py
WangluoJibengongXilie/js/libs/jquery.min.js
WangluoJibengongXilie/js/libs/localforage.min.js
WangluoJibengongXilie/js/libs/screenfull.js
WangluoJibengongXilie/js/libs/screenfull.min.js
WangluoJibengongXilie/js/libs/zip.min.js
WangluoJibengongXilie/js/plugins/__init__.py
wangluo_jibengong_xilie-2024.3.2.0.dist-info/METADATA
wangluo_jibengong_xilie-2024.3.2.0.dist-info/WHEEL
wangluo_jibengong_xilie-2024.3.2.0.dist-info/entry_points.txt
wangluo_jibengong_xilie-2024.3.2.0.dist-info/top_level.txt
wangluo_jibengong_xilie-2024.3.2.0.dist-info/RECORD
